{
    "type": "process",
    "bottom_solid_infill_flow_ratio": "0.97",
    "bridge_flow": "0.96",
    "brim_type": "auto_brim",
    "enable_arc_fitting": "1",
    "filename_format": "{input_filename_base}_{filament_type[initial_tool]}_{print_time}.gcode",
    "enable_prime_tower": "1",
    "exclude_object": "1",
    "from": "system",
    "setting_id": "GP004",
    "instantiation": "true",
    "compatible_printers": [
    "Flashforge AD5X 0.6 nozzle"
  ],
    "filter_out_gap_fill": "0.1",
    "gap_fill_target": "topbottom",
    "infill_wall_overlap": "20%",
    "inherits": "0.30mm Standard @Flashforge AD5M Pro 0.6 Nozzle",
    "internal_bridge_flow": "0.96",
    "is_custom_defined": "0",
    "name": "0.30mm Standard @FF AD5X 0.6 nozzle",
    "only_one_wall_top": "1",
    "prime_tower_brim_width": "6",
    "prime_tower_width": "30",
    "prime_volume": "60",
    "print_settings_id": "0.30mm Standard @FF AD5X 0.6 nozzle",
    "skirt_loops": "0",
    "slowdown_for_curled_perimeters": "0",
    "small_perimeter_speed": "25",
    "support_bottom_z_distance": "0.3",
    "support_line_width": "0.6",
    "support_top_z_distance": "0.3",
    "top_solid_infill_flow_ratio": "0.97",
    "version": "2.1.1.0",
    "wipe_tower_cone_angle": "10",
    "wipe_tower_extra_spacing": "110%"
}
