{
  "name": "Bambu PA-CF @Helio A1",
  "type": "filament",
  "inherits": "Bambu PA-CF @base",
  "instantiation": "true",
  "from": "system",
  "fan_cooling_layer_time": [
    "5"
  ],
  "nozzle_temperature": [
    "290"
  ],
  "full_fan_speed_layer": [
    "2"
  ],
  "fan_max_speed": [
    "30"
  ],
  "compatible_printers": [
    "Helio Bambu Lab A1 0.4 nozzle",
    "Helio Bambu Lab A1 0.6 nozzle",
    "Helio Bambu Lab A1 0.8 nozzle"
  ],
  "nozzle_temperature_initial_layer": [
    "290"
  ],
  "fan_min_speed": [
    "10"
  ],
  "setting_id": "GFSN03_01"
}