{
    "type": "filament",
    "name": "Vzbot Generic ASA",
    "inherits": "fdm_filament_asa",
    "from": "system",
    "setting_id": "GFSA04",
    "filament_id": "GFB98",
    "instantiation": "true",
    "filament_flow_ratio": [
        "0.93"
    ],
    "filament_max_volumetric_speed": [
        "50"
    ],
    "compatible_printers": [
        "Vzbot 235 AWD 0.4 nozzle",
        "Vzbot 330 AWD 0.4 nozzle",
        "Vzbot 235 AWD 0.5 nozzle",
        "Vzbot 235 AWD 0.6 nozzle",
        "Vzbot 330 AWD 0.5 nozzle",
        "Vzbot 330 AWD 0.6 nozzle"
    ]
}