{
    "type": "filament",
    "name": "fdm_filament_sbs",
    "inherits": "fdm_filament_common",
    "from": "system",
    "instantiation": "false",
    "fan_cooling_layer_time": [
        "100"
    ],
    "filament_max_volumetric_speed": [
        "23"
    ],
    "filament_type": [
      "SBS"
    ],
    "filament_density": [
        "1.02"
    ],
    "filament_cost": [
        "15"
    ],
    "cool_plate_temp": [
        "70"
    ],
    "eng_plate_temp": [
        "70"
    ],
    "hot_plate_temp": [
        "70"
    ],
    "textured_plate_temp": [
        "70"
    ],
    "cool_plate_temp_initial_layer": [
        "70"
    ],
    "eng_plate_temp_initial_layer": [
        "70"
    ],
    "hot_plate_temp_initial_layer": [
        "70"
    ],
    "textured_plate_temp_initial_layer": [
        "70"
    ],
    "nozzle_temperature_initial_layer": [
        "235"
    ],
    "reduce_fan_stop_start_freq": [
        "0"
    ],
    "fan_min_speed": [
        "0"
    ],
    "overhang_fan_threshold": [
        "50%"
    ],
    "close_fan_the_first_x_layers": [
        "3"
    ],
    "nozzle_temperature": [
        "235"
    ],
    "temperature_vitrification": [
        "70"
    ],
    "nozzle_temperature_range_low": [
        "215"
    ],
    "nozzle_temperature_range_high": [
        "250"
    ],
    "slow_down_min_speed": [
        "20"
    ],
    "slow_down_layer_time": [
        "4"
    ],
    "additional_cooling_fan_speed": [
        "40"
    ],
    "filament_start_gcode": [
        "; filament start gcode\n{if  (bed_temperature[current_extruder] >45)||(bed_temperature_initial_layer[current_extruder] >45)}M106 P3 S255\n{elsif(bed_temperature[current_extruder] >35)||(bed_temperature_initial_layer[current_extruder] >35)}M106 P3 S180\n{endif}\n\n{if activate_air_filtration[current_extruder] && support_air_filtration}\nM106 P3 S{during_print_exhaust_fan_speed_num[current_extruder]} \n{endif}"
    ]
}