{
	"type": "filament",
	"filament_id": "xxx",
	"setting_id": "xxx",
	"name": "Qidi Tech Generic PA",
	"from": "system",
	"instantiation": "true",
	"inherits": "fdm_filament_pa",
	"required_nozzle_HRC": [
		"3"
	],
	"nozzle_temperature_initial_layer": [
		"280"
	],
	"nozzle_temperature": [
		"280"
	],
	"filament_max_volumetric_speed": [
		"16"
	],
	"compatible_printers": [
		"Qidi Tech X-Smart3 0.4 nozzle",
		"Qidi Tech X-Plus3 0.4 nozzle",
		"Qidi Tech X-Max3 0.4 nozzle"
	]
}