{
    "type": "filament",
    "name": "Volumic ASA Ultra",
    "inherits": "fdm_filament_asa",
    "from": "system",
    "setting_id": "GFSA04",
    "filament_id": "GFB99",
    "instantiation": "true",
    "filament_flow_ratio": [
        "0.96"
    ],
    "nozzle_temperature": [
        "235"
    ],
    "hot_plate_temp": [
        "85"
    ],
    "fan_max_speed": [
        "30"
    ],
    "fan_min_speed": [
        "30"
    ],
    "filament_max_volumetric_speed": [
        "22"
    ],
    "compatible_printers": [
        "EXO42 (0.4 nozzle)",
        "EXO65 (0.6 nozzle)",
        "SH65 (0.4 nozzle)",
        "VS30MK3 (0.4 nozzle)",
        "VS30SC2 (0.4 nozzle)",
        "VS30SC (0.4 nozzle)",
        "VS30ULTRA (0.4 nozzle)",
        "VS30MK2 (0.4 nozzle)",
        "VS20MK2 (0.4 nozzle)",
        "EXO42 Stage 2 (0.4 nozzle)",
        "EXO65 Stage 2 (0.6 nozzle)",
        "SH65 Stage 2 (0.4 nozzle)",
        "VS30SC2 Stage 2 (0.4 nozzle)",
        "VS30MK3 Stage 2 (0.4 nozzle)"
    ]
}