{
    "fan_min_speed": [
        "0"
    ],
    "filament_retraction_length": [
        "3"
    ],
    "filament_retraction_speed": [
        "60"
    ],
    "filament_settings_id": [
        "Dremel Generic PLA @3D20 all"
    ],
    "from": "system",
    "inherits": "fdm_filament_common",
    "is_custom_defined": "0",
    "name": "Dremel Generic PLA @3D20 all",
    "nozzle_temperature": [
        "225"
    ],
    "nozzle_temperature_initial_layer": [
        "230"
    ],
    "nozzle_temperature_range_high": [
        "230"
    ],
    "slow_down_min_speed": [
        "10"
    ],
    "version": "1.7.0.2"
}
