{
    "type": "process",
    "name": "0.30mm Strength @BBL P1P 0.6 nozzle",
    "inherits": "fdm_process_single_0.30_nozzle_0.6",
    "from": "system",
    "setting_id": "GP067",
    "instantiation": "true",
    "description": "Compared with the default profile of a 0.6 mm nozzle, it has more wall loops and a higher sparse infill density. So, it results in higher strength of the prints, but more filament consumption and longer printing time.",
    "elefant_foot_compensation": "0.15",
    "sparse_infill_density": "25%",
    "skeleton_infill_density": "25%",
    "skin_infill_density": "25%",
    "wall_loops": "4",
    "compatible_printers": [
        "Bambu Lab P1P 0.6 nozzle"
    ]
}