{
    "type": "filament",
    "name": "Fiberon PA612-CF @base",
    "inherits": "fdm_filament_pa",
    "from": "system",
    "filament_id": "OGFL53",
    "instantiation": "false",
    "fan_cooling_layer_time": [
        "5"
    ],
    "fan_max_speed": [
        "30"
    ],
    "fan_min_speed": [
        "10"
    ],
    "filament_cost": [
        "94.99"
    ],
    "filament_density": [
        "1.06"
    ],
    "filament_flow_ratio": [
        "0.96"
    ],
    "filament_vendor": [
        "Polymaker"
    ],
    "full_fan_speed_layer": [
        "2"
    ],
    "overhang_fan_speed": [
        "40"
    ],
    "overhang_fan_threshold": [
        "0%"
    ],
    "temperature_vitrification": [
        "180"
    ]
}