{
    "type": "filament",
    "filament_id": "GFL98",
    "setting_id": "GFSL98",
    "name": "Generic PLA-CF",
    "from": "system",
    "instantiation": "true",
    "inherits": "fdm_filament_pla",
    "filament_flow_ratio": [
        "0.95"
    ],
    "filament_type": [
        "PLA-CF"
    ],
    "filament_max_volumetric_speed": [
        "12"
    ],
    "slow_down_layer_time": [
        "7"
    ],
    "additional_cooling_fan_speed": [
        "0"
    ],
    "compatible_printers": [
      "Bambu Lab X1 Carbon 0.4 nozzle",
      "Bambu Lab X1 Carbon 0.6 nozzle",
      "Bambu Lab X1 Carbon 0.8 nozzle"
    ]
}
