{
    "name": "AnkerMake",
    "version": "01.09.00.01",
    "force_update": "0",
    "description": "AnkerMake configurations",
    "machine_model_list": [
        {
            "name": "AnkerMake M5",
            "sub_path": "machine/AnkerMake M5.json"
        },
        {
            "name": "AnkerMake M5c",
            "sub_path": "machine/AnkerMake M5c.json"
        }
    ],
    "process_list": [
        {
            "name": "fdm_process_common",
            "sub_path": "process/fdm_process_common.json"
        },
        {
            "name": "fdm_process_ankermake_common",
            "sub_path": "process/fdm_process_ankermake_common.json"
        },
        {
            "name": "fdm_process_ankermake_fast_common",
            "sub_path": "process/fdm_process_ankermake_fast_common.json"
        },
        /*{
            "name": "fdm_process_ankermake_common_0_2",
            "sub_path": "process/fdm_process_ankermake_common_0_2.json"
        },
        {
            "name": "fdm_process_ankermake_common_0_2_5",
            "sub_path": "process/fdm_process_ankermake_common_0_2_5.json"
        },
        {
            "name": "fdm_process_ankermake_common_0_6",
            "sub_path": "process/fdm_process_ankermake_common_0_6.json"
        },
        {
            "name": "fdm_process_ankermake_common_0_8",
            "sub_path": "process/fdm_process_ankermake_common_0_8.json"
        },
        {
            "name": "0.05mm Ultradetail 0.2 nozzle @AnkerMake",
            "sub_path": "process/0.05mm Ultradetail 0.2 nozzle @AnkerMake.json"
        },
        {
            "name": "0.05mm Ultradetail 0.25 nozzle @AnkerMake",
            "sub_path": "process/0.05mm Ultradetail 0.25 nozzle @AnkerMake.json"
        },*/
        {
            "name": "0.05mm Ultradetail @AnkerMake",
            "sub_path": "process/0.05mm Ultradetail @AnkerMake.json"
        },
        /*{
            "name": "0.10mm Detail 0.2 nozzle @AnkerMake",
            "sub_path": "process/0.10mm Detail 0.2 nozzle @AnkerMake.json"
        },
        {
            "name": "0.10mm Detail 0.25 nozzle @AnkerMake",
            "sub_path": "process/0.10mm Detail 0.25 nozzle @AnkerMake.json"
        },*/
        {
            "name": "0.10mm Detail @AnkerMake",
            "sub_path": "process/0.10mm Detail @AnkerMake.json"
        },
        /*{
            "name": "0.15mm Optimal 0.2 nozzle @AnkerMake",
            "sub_path": "process/0.15mm Optimal 0.2 nozzle @AnkerMake.json"
        },
        {
            "name": "0.15mm Optimal 0.25 nozzle @AnkerMake",
            "sub_path": "process/0.15mm Optimal 0.25 nozzle @AnkerMake.json"
        },*/
        {
            "name": "0.15mm Optimal @AnkerMake",
            "sub_path": "process/0.15mm Optimal @AnkerMake.json"
        },
        {
            "name": "0.15mm Fast @AnkerMake",
            "sub_path": "process/0.15mm Fast @AnkerMake.json"
        },
        /*{
            "name": "0.18mm Fine 0.6 nozzle @AnkerMake",
            "sub_path": "process/0.18mm Fine 0.6 nozzle @AnkerMake.json"
        },*/
        {
            "name": "0.20mm Standard @AnkerMake",
            "sub_path": "process/0.20mm Standard @AnkerMake.json"
        },
        {
            "name": "0.20mm Fast @AnkerMake",
            "sub_path": "process/0.20mm Fast @AnkerMake.json"
        },
        {
            "name": "0.25mm Draft @AnkerMake",
            "sub_path": "process/0.25mm Draft @AnkerMake.json"
        },
        {
            "name": "0.25mm Fast @AnkerMake",
            "sub_path": "process/0.25mm Fast @AnkerMake.json"
        },
        /*{
            "name": "0.24mm Optimal 0.6 nozzle @AnkerMake",
            "sub_path": "process/0.24mm Optimal 0.6 nozzle @AnkerMake.json"
        },
        {
            "name": "0.24mm Fine 0.8 nozzle @AnkerMake",
            "sub_path": "process/0.24mm Fine 0.8 nozzle @AnkerMake.json"
        },*/
        {
            "name": "0.30mm Extra Draft @AnkerMake",
            "sub_path": "process/0.30mm Extra Draft @AnkerMake.json"
        }
        /*{
            "name": "0.30mm Standard 0.6 nozzle @AnkerMake",
            "sub_path": "process/0.30mm Standard 0.6 nozzle @AnkerMake.json"
        },
        {
            "name": "0.32mm Optimal 0.6 nozzle @AnkerMake",
            "sub_path": "process/0.32mm Optimal 0.6 nozzle @AnkerMake.json"
        },
        {
            "name": "0.36mm Draft 0.6 nozzle @AnkerMake",
            "sub_path": "process/0.36mm Draft 0.6 nozzle @AnkerMake.json"
        },
        {
            "name": "0.40mm Standard 0.8 nozzle @AnkerMake",
            "sub_path": "process/0.40mm Standard 0.8 nozzle @AnkerMake.json"
        },
        {
            "name": "0.42mm Extra Draft 0.6 nozzle @AnkerMake",
            "sub_path": "process/0.42mm Extra Draft 0.6 nozzle @AnkerMake.json"
        },
        {
            "name": "0.48mm Draft 0.8 nozzle @AnkerMake",
            "sub_path": "process/0.48mm Draft 0.8 nozzle @AnkerMake.json"
        },
        {
            "name": "0.56mm Extra Draft 0.8 nozzle @AnkerMake",
            "sub_path": "process/0.56mm Extra Draft 0.8 nozzle @AnkerMake.json"
        }*/
    ],
    "filament_list": [
        {
            "name": "fdm_filament_common",
            "sub_path": "filament/fdm_filament_common.json"
        },
        {
            "name": "fdm_filament_pla",
            "sub_path": "filament/fdm_filament_pla.json"
        },
        {
            "name": "fdm_filament_tpu",
            "sub_path": "filament/fdm_filament_tpu.json"
        },
        {
            "name": "fdm_filament_pet",
            "sub_path": "filament/fdm_filament_pet.json"
        },
        {
            "name": "fdm_filament_abs",
            "sub_path": "filament/fdm_filament_abs.json"
        },
        {
            "name": "fdm_filament_pc",
            "sub_path": "filament/fdm_filament_pc.json"
        },
        {
            "name": "fdm_filament_asa",
            "sub_path": "filament/fdm_filament_asa.json"
        },
        {
            "name": "fdm_filament_pva",
            "sub_path": "filament/fdm_filament_pva.json"
        },
        {
            "name": "fdm_filament_pa ",
            "sub_path": "filament/fdm_filament_pa .json"
        },
        {
            "name": "AnkerMake PLA+ @base",
            "sub_path": "filament/AnkerMake PLA+ @base.json"
        },
        {
            "name": "Generic PLA @base",
            "sub_path": "filament/Generic PLA @base.json"
        },
        {
            "name": "Generic PLA+ @base",
            "sub_path": "filament/Generic PLA+ @base.json"
        },
        {
            "name": "Generic High Speed PLA+ @base",
            "sub_path": "filament/Generic High Speed PLA+ @base.json"
        },
        {
            "name": "Generic PLA Silk @base",
            "sub_path": "filament/Generic PLA Silk @base.json"
        },
        {
            "name": "Generic PLA-CF @base",
            "sub_path": "filament/Generic PLA-CF @base.json"
        },
        {
            "name": "Generic TPU @base",
            "sub_path": "filament/Generic TPU @base.json"
        },
        {
            "name": "Generic PETG @base",
            "sub_path": "filament/Generic PETG @base.json"
        },
        {
            "name": "Generic PETG-CF @base",
            "sub_path": "filament/Generic PETG-CF @base.json"
        },
        {
            "name": "Generic ABS @base",
            "sub_path": "filament/Generic ABS @base.json"
        },
        {
            "name": "Generic ASA @base",
            "sub_path": "filament/Generic ASA @base.json"
        },
        {
            "name": "Generic PC @base",
            "sub_path": "filament/Generic PC @base.json"
        },
        {
            "name": "Generic PVA @base",
            "sub_path": "filament/Generic PVA @base.json"
        },
        {
            "name": "Generic PA @base",
            "sub_path": "filament/Generic PA @base.json"
        },
        {
            "name": "Generic PA-CF @base",
            "sub_path": "filament/Generic PA-CF @base.json"
        },
        {
            "name": "AnkerMake PLA+",
            "sub_path": "filament/AnkerMake PLA+.json"
        },
        {
            "name": "AnkerMake PLA+ @0.2 nozzle",
            "sub_path": "filament/AnkerMake PLA+ @0.2 nozzle.json"
        },
                {
            "name": "Generic PLA",
            "sub_path": "filament/Generic PLA.json"
        },
        {
            "name": "Generic PLA @0.2 nozzle",
            "sub_path": "filament/Generic PLA @0.2 nozzle.json"
        },
        {
            "name": "Generic PLA+",
            "sub_path": "filament/Generic PLA+.json"
        },
        {
            "name": "Generic PLA+ @0.2 nozzle",
            "sub_path": "filament/Generic PLA+ @0.2 nozzle.json"
        },
        {
            "name": "Generic High Speed PLA+",
            "sub_path": "filament/Generic High Speed PLA+.json"
        },
        {
            "name": "Generic High Speed PLA+ @0.2 nozzle",
            "sub_path": "filament/Generic High Speed PLA+ @0.2 nozzle.json"
        },
        {
            "name": "Generic PLA Silk",
            "sub_path": "filament/Generic PLA Silk.json"
        },
        {
            "name": "Generic PLA Silk @0.2 nozzle",
            "sub_path": "filament/Generic PLA Silk @0.2 nozzle.json"
        },
        {
            "name": "Generic PLA-CF",
            "sub_path": "filament/Generic PLA-CF.json"
        },
        {
            "name": "Generic PLA-CF @0.2 nozzle",
            "sub_path": "filament/Generic PLA-CF @0.2 nozzle.json"
        },
        {
            "name": "Generic TPU",
            "sub_path": "filament/Generic TPU.json"
        },
        {
            "name": "Generic TPU @0.2 nozzle",
            "sub_path": "filament/Generic TPU @0.2 nozzle.json"
        },
        {
            "name": "Generic PETG",
            "sub_path": "filament/Generic PETG.json"
        },
        {
            "name": "Generic PETG @0.2 nozzle",
            "sub_path": "filament/Generic PETG @0.2 nozzle.json"
        },
        {
            "name": "Generic PETG-CF",
            "sub_path": "filament/Generic PETG-CF.json"
        },
        {
            "name": "Generic PETG-CF @0.2 nozzle",
            "sub_path": "filament/Generic PETG-CF @0.2 nozzle.json"
        },
        {
            "name": "Generic ABS",
            "sub_path": "filament/Generic ABS.json"
        },
        {
            "name": "Generic ABS @0.2 nozzle",
            "sub_path": "filament/Generic ABS @0.2 nozzle.json"
        },
        {
            "name": "Generic ASA",
            "sub_path": "filament/Generic ASA.json"
        },
        {
            "name": "Generic ASA @0.2 nozzle",
            "sub_path": "filament/Generic ASA @0.2 nozzle.json"
        },
        {
            "name": "Generic PC",
            "sub_path": "filament/Generic PC.json"
        },
        {
            "name": "Generic PC @0.2 nozzle",
            "sub_path": "filament/Generic PC @0.2 nozzle.json"
        },
        {
            "name": "Generic PVA",
            "sub_path": "filament/Generic PVA.json"
        },
        {
            "name": "Generic PVA @0.2 nozzle",
            "sub_path": "filament/Generic PVA @0.2 nozzle.json"
        },
        {
            "name": "Generic PA",
            "sub_path": "filament/Generic PA.json"
        },
        {
            "name": "Generic PA @0.2 nozzle",
            "sub_path": "filament/Generic PA @0.2 nozzle.json"
        },
        {
            "name": "Generic PA-CF",
            "sub_path": "filament/Generic PA-CF.json"
        },
        {
            "name": "Generic PA-CF @0.2 nozzle",
            "sub_path": "filament/Generic PA-CF @0.2 nozzle.json"
        }
    ],
    "machine_list": [
        {
            "name": "fdm_machine_common",
            "sub_path": "machine/fdm_machine_common.json"
        },
        {
            "name": "fdm_marlin_common",
            "sub_path": "machine/fdm_marlin_common.json"
        },
        {
            "name": "AnkerMake M5 PTFE 0.4 nozzle",
            "sub_path": "machine/AnkerMake M5 PTFE 0.4 nozzle.json"
        },
        /*{
            "name": "AnkerMake M5 PTFE 0.4 PCD nozzle",
            "sub_path": "machine/AnkerMake M5 PTFE 0.4 PCD nozzle.json"
        },
        {
            "name": "AnkerMake M5 PTFE 0.2 nozzle",
            "sub_path": "machine/AnkerMake M5 PTFE 0.2 nozzle.json"
        },
        {
            "name": "AnkerMake M5 PTFE 0.25 PCD nozzle",
            "sub_path": "machine/AnkerMake M5 PTFE 0.25 PCD nozzle.json"
        },
        {
            "name": "AnkerMake M5 PTFE 0.6 nozzle",
            "sub_path": "machine/AnkerMake M5 PTFE 0.6 nozzle.json"
        },
        {
            "name": "AnkerMake M5 PTFE 0.6 PCD nozzle",
            "sub_path": "machine/AnkerMake M5 PTFE 0.6 PCD nozzle.json"
        },
        {
            "name": "AnkerMake M5 PTFE 0.8 nozzle",
            "sub_path": "machine/AnkerMake M5 PTFE 0.8 nozzle.json"
        },
        {
            "name": "AnkerMake M5 PTFE 0.8 PCD nozzle",
            "sub_path": "machine/AnkerMake M5 PTFE 0.8 PCD nozzle.json"
        },*/
        {
            "name": "AnkerMake M5 All-Metal 0.4 nozzle",
            "sub_path": "machine/AnkerMake M5 All-Metal 0.4 nozzle.json"
        },
        /*{
            "name": "AnkerMake M5 All-Metal PCD 0.4 nozzle",
            "sub_path": "machine/AnkerMake M5 All-Metal PCD 0.4 nozzle.json"
        },
        {
            "name": "AnkerMake M5 All-Metal 0.2 nozzle",
            "sub_path": "machine/AnkerMake M5 All-Metal 0.2 nozzle.json"
        },
        {
            "name": "AnkerMake M5 All-Metal 0.25 PCD nozzle",
            "sub_path": "machine/AnkerMake M5 All-Metal 0.25 PCD nozzle.json"
        },
        {
            "name": "AnkerMake M5 All-Metal 0.6 nozzle",
            "sub_path": "machine/AnkerMake M5 All-Metal 0.6 nozzle.json"
        },
        {
            "name": "AnkerMake M5 All-Metal 0.6 PCD nozzle",
            "sub_path": "machine/AnkerMake M5 All-Metal 0.6 PCD nozzle.json"
        },
        {
            "name": "AnkerMake M5 All-Metal 0.8 nozzle",
            "sub_path": "machine/AnkerMake M5 All-Metal 0.8 nozzle.json"
        },
        {
            "name": "AnkerMake M5 All-Metal 0.8 PCD nozzle",
            "sub_path": "machine/AnkerMake M5 All-Metal 0.8 PCD nozzle.json"
        },*/
        {
            "name": "AnkerMake M5c 0.4 nozzle",
            "sub_path": "machine/AnkerMake M5c 0.4 nozzle.json"
        }
        /*{
            "name": "AnkerMake M5c 0.4 PCD nozzle",
            "sub_path": "machine/AnkerMake M5c 0.4 PCD nozzle.json"
        },
        {
            "name": "AnkerMake M5c 0.2 nozzle",
            "sub_path": "machine/AnkerMake M5c 0.2 nozzle.json"
        },
        {
            "name": "AnkerMake M5c 0.25 PCD nozzle",
            "sub_path": "machine/AnkerMake M5c 0.25 PCD nozzle.json"
        },
        {
            "name": "AnkerMake M5c 0.6 nozzle",
            "sub_path": "machine/AnkerMake M5c 0.6 nozzle.json"
        },
        {
            "name": "AnkerMake M5c 0.6 PCD nozzle",
            "sub_path": "machine/AnkerMake M5c 0.6 PCD nozzle.json"
        },
        {
            "name": "AnkerMake M5c 0.8 nozzle",
            "sub_path": "machine/AnkerMake M5c 0.8 nozzle.json"
        },
        {
            "name": "AnkerMake M5c 0.8 PCD nozzle",
            "sub_path": "machine/AnkerMake M5c 0.8 PCD nozzle.json"
        }*/
    ]
}
